mecab_ko/_MeCab.cpython-313-x86_64-linux-gnu.so
mecab_ko/__init__.py
mecab_ko/cli.py
mecab_ko.libs/libmecab-46dbe3bb.so.2.0.0
mecab_ko-1.0.2.dist-info/METADATA
mecab_ko-1.0.2.dist-info/WHEEL
mecab_ko-1.0.2.dist-info/entry_points.txt
mecab_ko-1.0.2.dist-info/top_level.txt
mecab_ko-1.0.2.dist-info/RECORD
mecab_ko-1.0.2.dist-info/licenses/AUTHORS
mecab_ko-1.0.2.dist-info/licenses/COPYING
