Metadata-Version: 2.1
Name: mecab-ko
Version: 1.0.2
Summary: Python wrapper for the MeCab-ko morphological analyzer for Korean
Home-page: https://github.com/NoUnique/pymecab-ko
Maintainer: Taehwan Yoo
Maintainer-email: kofmap@gmail.com
License: BSD
Platform: UNKNOWN
Classifier: Development Status :: 6 - Mature
Classifier: Programming Language :: Python :: 3
Classifier: Programming Language :: Python :: 3.8
Classifier: Programming Language :: Python :: 3.9
Classifier: Programming Language :: Python :: 3.10
Classifier: Programming Language :: Python :: 3.11
Classifier: Programming Language :: Python :: 3.12
Classifier: Programming Language :: Python :: 3.13
Classifier: Intended Audience :: Developers
Classifier: Intended Audience :: Science/Research
Classifier: Natural Language :: Korean
Classifier: Topic :: Software Development :: Libraries :: Python Modules
Classifier: Topic :: Text Processing :: Linguistic
Classifier: License :: OSI Approved :: BSD License
License-File: COPYING
License-File: AUTHORS
Requires-Dist: mecab-ko-dic (<2.0,>=1.0)
